rake/__init__.py
rake/rake.py
rake/stoplists.py
rake/data/stoplists/FoxStoplist.txt
rake/data/stoplists/SmartStoplist.txt
TopicAxis_RAKE-0.1.0.dist-info/METADATA
TopicAxis_RAKE-0.1.0.dist-info/WHEEL
TopicAxis_RAKE-0.1.0.dist-info/top_level.txt
TopicAxis_RAKE-0.1.0.dist-info/RECORD
