Metadata-Version: 2.1
Name: TopicAxis-RAKE
Version: 0.1.0
Summary: Text keyword extraction library
Home-page: https://github.com/topicaxis/RAKE
Author: Panagiotis Matigakis
Author-email: pmatigakis@gmail.com
License: UNKNOWN
Platform: UNKNOWN
Classifier: Development Status :: 3 - Alpha
Classifier: Intended Audience :: Developers
Classifier: Natural Language :: English
Classifier: License :: OSI Approved :: MIT License
Classifier: Programming Language :: Python
Classifier: Programming Language :: Python :: 3
Classifier: Programming Language :: Python :: 3.5
Classifier: Programming Language :: Python :: Implementation :: CPython
Classifier: Operating System :: OS Independent
